MANIFEST.in
README.rst
setup.py
bvtextprocessing/__init__.py
bvtextprocessing/ngrams.py
bvtextprocessing/stem.py
bvtextprocessing.egg-info/PKG-INFO
bvtextprocessing.egg-info/SOURCES.txt
bvtextprocessing.egg-info/dependency_links.txt
bvtextprocessing.egg-info/not-zip-safe
bvtextprocessing.egg-info/requires.txt
bvtextprocessing.egg-info/top_level.txt